README.md
setup.py
langsplit/__init__.py
langsplit/extras.py
langsplit/splitter.py
langsplit.egg-info/PKG-INFO
langsplit.egg-info/SOURCES.txt
langsplit.egg-info/dependency_links.txt
langsplit.egg-info/not-zip-safe
langsplit.egg-info/requires.txt
langsplit.egg-info/top_level.txt