Metadata-Version: 2.1
Name: langsplit
Version: 0.2.5
Summary: Splits text by separator, and limited length language names, combines split text chunks into OrderedDict, or combines back to text. Supposed for extending markdown with tags for human languages.
Home-page: https://github.com/mindey/langsplit
Author: Mindey
Author-email: mindey@qq.com
License: UNLICENSE
Platform: UNKNOWN
Provides-Extra: test
